README.md
setup.cfg
setup.py
pyopls/__init__.py
pyopls/kernel_density.py
pyopls/opls.py
pyopls/permutation_test.py
pyopls/validation.py
pyopls.egg-info/PKG-INFO
pyopls.egg-info/SOURCES.txt
pyopls.egg-info/dependency_links.txt
pyopls.egg-info/requires.txt
pyopls.egg-info/top_level.txt