Metadata-Version: 2.1
Name: pyopls
Version: 20.3
Summary: Orthogonal Projection to Latent Structures
Home-page: https://github.com/BiRG/pyopls
Author: BiRG @ Wright State University
Author-email: foose.3@wright.edu
License: UNKNOWN
Download-URL: https://github.com/BiRG/pyopls/archive/20.02.tar.gz
Keywords: metabolomics chemometrics partial-least-squares
Platform: UNKNOWN
Classifier: Natural Language :: English
Classifier: Intended Audience :: Science/Research
Classifier: Programming Language :: Python :: 3.6
Classifier: Programming Language :: Python :: 3.7
Classifier: Programming Language :: Python :: 3.8
Classifier: Programming Language :: Python :: 3.9
Classifier: License :: OSI Approved :: MIT License
Classifier: Operating System :: OS Independent
Requires-Python: >=3.5
